sqlboy/__init__.py
sqlboy-1.1.dist-info/LICENSE
sqlboy-1.1.dist-info/METADATA
sqlboy-1.1.dist-info/WHEEL
sqlboy-1.1.dist-info/top_level.txt
sqlboy-1.1.dist-info/RECORD
