Metadata-Version: 2.1
Name: sqlboy
Version: 1.1
Summary: A python package for sql ana
Home-page: UNKNOWN
Author: liyurun
Author-email: 1404020204@s.upc.edu.cn
License: UNKNOWN
Platform: UNKNOWN
Classifier: Programming Language :: Python :: 3
Classifier: License :: OSI Approved :: MIT License
Classifier: Operating System :: OS Independent
Requires-Python: >=3
License-File: LICENSE
